bankreader/__init__.py
bankreader/admin.py
bankreader/apps.py
bankreader/locale/cs/LC_MESSAGES/django.mo
bankreader/locale/cs/LC_MESSAGES/django.po
bankreader/management/__init__.py
bankreader/management/commands/__init__.py
bankreader/management/commands/loadbankstatement.py
bankreader/migrations/0001_initial.py
bankreader/migrations/0002_transaction_account_statement.py
bankreader/migrations/0003_transaction_account_statement_cleanup.py
bankreader/migrations/0004_defaults.py
bankreader/migrations/0005_alter_transaction_unique_together_alter_account_id_and_more.py
bankreader/migrations/__init__.py
bankreader/models.py
bankreader/readers/__init__.py
bankreader/readers/base.py
bankreader/readers/best.py
bankreader/readers/csv.py
bankreader/readers/gpc.py
bankreader/readers/mt940.py
bankreader_demo/__init__.py
bankreader_demo/asgi.py
bankreader_demo/demoapp/__init__.py
bankreader_demo/demoapp/admin.py
bankreader_demo/demoapp/apps.py
bankreader_demo/demoapp/migrations/0001_initial.py
bankreader_demo/demoapp/migrations/0002_alter_order_id_alter_orderpayment_id.py
bankreader_demo/demoapp/migrations/__init__.py
bankreader_demo/demoapp/models.py
bankreader_demo/demoapp/readers.py
bankreader_demo/settings.py
bankreader_demo/urls.py
bankreader_demo/wsgi.py
django_bankreader-1.5.0.dist-info/METADATA
django_bankreader-1.5.0.dist-info/WHEEL
django_bankreader-1.5.0.dist-info/licenses/LICENSE
django_bankreader-1.5.0.dist-info/RECORD
