Metadata-Version: 2.4
Name: django-bankreader
Version: 1.5.0
Summary: Pluggable django application for reading and processing various formats of bank account statements
License: BSD-3-Clause
License-File: LICENSE
Author: Jakub Dorňák
Author-email: jakub.dornak@qbsoftware.cz
Requires-Python: >=3.10
Classifier: Development Status :: 5 - Production/Stable
Classifier: Environment :: Web Environment
Classifier: Framework :: Django
Classifier: Framework :: Django :: 3
Classifier: Intended Audience :: Developers
Classifier: License :: OSI Approved :: BSD License
Classifier: Natural Language :: Czech
Classifier: Natural Language :: English
Classifier: Operating System :: OS Independent
Classifier: Programming Language :: Python
Classifier: Programming Language :: Python :: 3
Classifier: Programming Language :: Python :: 3.10
Classifier: Programming Language :: Python :: 3.11
Classifier: Programming Language :: Python :: 3.12
Classifier: Programming Language :: Python :: 3.13
Classifier: Programming Language :: Python :: 3.14
Requires-Dist: Django (>=3.0)
Requires-Dist: django-localflavor
Requires-Dist: mt-940
Project-URL: Repository, https://github.com/qbsoftware/django-bankreader
